starlasuspecs/__init__.py
starlasuspecs/constants.py
starlasuspecs/py.typed
starlasuspecs/utils.py
starlasuspecs/v1/__init__.py
starlasuspecs/v1/ast_language.py
starlasuspecs/v1/codebase_language.py
starlasuspecs/v1/comments_language.py
starlasuspecs/v1/migration_language.py
starlasuspecs/v1/pipeline_language.py
starlasuspecs/v1/types_language.py
starlasuspecs/v2/__init__.py
starlasuspecs/v2/ast_language.py
starlasuspecs/v2/codebase_language.py
tests/__init__.py
tests/test_pipeline_language_v1.py
tests/test_starlasu_language_v1.py
starlasu_specs-0.6.4.dist-info/METADATA
starlasu_specs-0.6.4.dist-info/WHEEL
starlasu_specs-0.6.4.dist-info/top_level.txt
starlasu_specs-0.6.4.dist-info/RECORD
