Metadata-Version: 2.4
Name: starlasu-specs
Version: 0.6.4
Summary: Starlasu Specs
Author: Federico Tomassetti
Author-email: federico@strumenta.com
Requires-Python: >=3.11
Requires-Dist: lionweb>=0.3.7
Requires-Dist: requests>=2.32.3
Dynamic: author
Dynamic: author-email
Dynamic: requires-dist
Dynamic: requires-python
Dynamic: summary
